search_repo/__init__.py
search_repo/__main__.py
search_repo-0.2.2.dist-info/entry_points.txt
search_repo-0.2.2.dist-info/WHEEL
search_repo-0.2.2.dist-info/METADATA
search_repo-0.2.2.dist-info/RECORD
