Metadata-Version: 2.1
Name: search-repo
Version: 0.2.2
Summary: Search for a github repo
Home-page: https://github.com/Tadaboody/search_repo
License: MIT
Author: Tomer Keren
Author-email: tomer.keren.dev@gmail.com
Requires-Python: >=3.6,<4.0
Classifier: License :: OSI Approved :: MIT License
Classifier: Programming Language :: Python :: 3
Classifier: Programming Language :: Python :: 3.6
Classifier: Programming Language :: Python :: 3.7
Classifier: Programming Language :: Python :: 3.8
Requires-Dist: aiohttp (>=3.6.2,<4.0.0)
Project-URL: Repository, https://github.com/Tadaboody/search_repo
